{
  "slug": "privacy-policy",
  "title": "Privacy Policy",
  "parent": 0,
  "menu_order": 0,
  "blocks": [
    {
      "type": "heading",
      "level": 2,
      "text": "Privacy Policy"
    },
    {
      "type": "text",
      "text": "Effective Date: November 2025Last Updated: November 2025"
    },
    {
      "type": "heading",
      "level": 3,
      "text": "1. Introduction"
    },
    {
      "type": "text",
      "text": "At Jinhao Xinyuan Group, your privacy is important to us. This Privacy Policy explains how we collect, use, and protect your personal data when you visit jinhaoxy.com, contact us, or engage our packaging and printing services."
    },
    {
      "type": "text",
      "text": "We operate manufacturing facilities in Vietnam and China, serving clients worldwide. All data is processed in accordance with applicable data protection laws including the EU GDPR and equivalent regional standards."
    },
    {
      "type": "heading",
      "level": 3,
      "text": "2. Data We Collect"
    },
    {
      "type": "text",
      "text": "We may collect the following information:"
    },
    {
      "type": "text",
      "text": "• Contact Information: name, email address, phone number, and company name."
    },
    {
      "type": "text",
      "text": "Contact Information: name, email address, phone number, and company name."
    },
    {
      "type": "text",
      "text": "• Business Information: inquiries, project requirements, and communication history."
    },
    {
      "type": "text",
      "text": "Business Information: inquiries, project requirements, and communication history."
    },
    {
      "type": "text",
      "text": "• Technical Information: IP address, browser type, pages visited, and cookies for analytics."
    },
    {
      "type": "text",
      "text": "Technical Information: IP address, browser type, pages visited, and cookies for analytics."
    },
    {
      "type": "text",
      "text": "• Marketing Preferences: newsletter subscriptions and consent records."
    },
    {
      "type": "text",
      "text": "Marketing Preferences: newsletter subscriptions and consent records."
    },
    {
      "type": "heading",
      "level": 3,
      "text": "3. How We Use Your Data"
    },
    {
      "type": "text",
      "text": "We use your data to:"
    },
    {
      "type": "text",
      "text": "• Respond to inquiries and provide quotations."
    },
    {
      "type": "text",
      "text": "Respond to inquiries and provide quotations."
    },
    {
      "type": "text",
      "text": "• Process and deliver packaging orders."
    },
    {
      "type": "text",
      "text": "Process and deliver packaging orders."
    },
    {
      "type": "text",
      "text": "• Improve our website and customer experience."
    },
    {
      "type": "text",
      "text": "Improve our website and customer experience."
    },
    {
      "type": "text",
      "text": "• Maintain legal, accounting, and compliance obligations."
    },
    {
      "type": "text",
      "text": "Maintain legal, accounting, and compliance obligations."
    },
    {
      "type": "text",
      "text": "• Send marketing updates (only with your consent)."
    },
    {
      "type": "text",
      "text": "Send marketing updates (only with your consent)."
    },
    {
      "type": "text",
      "text": "We never sell or rent your information to third parties."
    },
    {
      "type": "heading",
      "level": 3,
      "text": "4. Data Retention"
    },
    {
      "type": "text",
      "text": "We retain your personal data only as long as necessary for business, accounting, or legal purposes. Once no longer required, it is securely deleted."
    },
    {
      "type": "heading",
      "level": 3,
      "text": "5. Cookies"
    },
    {
      "type": "text",
      "text": "Our website uses cookies to analyze traffic, enhance functionality, and personalize content.You can manage cookie preferences via your browser settings or our Cookie Policy."
    },
    {
      "type": "heading",
      "level": 3,
      "text": "6. Third-Party Services"
    },
    {
      "type": "text",
      "text": "We may use third-party services (e.g., Google Analytics, WordPress plugins, or CRM systems) that comply with international data protection standards. Each processor is contractually bound to safeguard your data."
    },
    {
      "type": "heading",
      "level": 3,
      "text": "7. Your Rights"
    },
    {
      "type": "text",
      "text": "Depending on your jurisdiction, you have the right to:"
    },
    {
      "type": "text",
      "text": "• Access, correct, or delete your personal data."
    },
    {
      "type": "text",
      "text": "Access, correct, or delete your personal data."
    },
    {
      "type": "text",
      "text": "• Withdraw consent for marketing."
    },
    {
      "type": "text",
      "text": "Withdraw consent for marketing."
    },
    {
      "type": "text",
      "text": "• Request data portability."
    },
    {
      "type": "text",
      "text": "Request data portability."
    },
    {
      "type": "text",
      "text": "• File a complaint with your local data authority."
    },
    {
      "type": "text",
      "text": "File a complaint with your local data authority."
    },
    {
      "type": "text",
      "text": "To exercise these rights, email us at info@jinhaoxy.com."
    },
    {
      "type": "heading",
      "level": 3,
      "text": "8. International Data Transfers"
    },
    {
      "type": "text",
      "text": "Data may be processed in our regional offices in Vietnam and China, under strict confidentiality and data protection agreements."
    },
    {
      "type": "heading",
      "level": 3,
      "text": "9. Security"
    },
    {
      "type": "text",
      "text": "We implement appropriate technical and organizational measures to prevent unauthorized access, disclosure, or loss of your personal data."
    },
    {
      "type": "heading",
      "level": 3,
      "text": "10. Updates to This Policy"
    },
    {
      "type": "text",
      "text": "We may revise this Privacy Policy periodically. The latest version will always be available on this page."
    },
    {
      "type": "heading",
      "level": 3,
      "text": "11. Contact Us"
    },
    {
      "type": "text",
      "text": "Jinhao Xinyuan GroupNo.8 Jiankang Road, Donggang Town, Xishan District, Wuxi City, Jiangsu Province, China📞 +84-0907093845 ✉️ info@jinhaoxy.com"
    }
  ],
  "faqs": []
}