{
  "slug": "folding-cartons",
  "title": "Thùng carton gấp",
  "parent": 0,
  "menu_order": 0,
  "blocks": [
    {
      "type": "heading",
      "level": 1,
      "text": "Nhà sản xuất thùng carton gấp Việt Nam – Bao bì tiêu dùng in chính xác"
    },
    {
      "type": "text",
      "text": "XinYuan sản xuất thùng carton gấp kết hợp cấu trúc, tính bền vững và sức hấp dẫn trên kệ nổi bật. Các cơ sở sản xuất của chúng tôi tại Việt Nam và Trung Quốc cung cấp thùng carton in chất lượng cao cho các thương hiệu bán lẻ, mỹ phẩm, thực phẩm, điện tử và FMCG trên toàn thế giới. Mỗi hộp đều được thiết kế để có độ bền, độ chính xác và hiệu quả tự động, đảm bảo sản phẩm của bạn đến nơi an toàn và trông đặc biệt tại điểm bán hàng."
    },
    {
      "type": "text",
      "text": "Các tính năng chính:"
    },
    {
      "type": "text",
      "text": "• In offset và kỹ thuật số cao cấp cho sự nhất quán màu sắc hoàn hảo"
    },
    {
      "type": "text",
      "text": "In offset và kỹ thuật số cao cấp cho màu sắc nhất quán hoàn hảo"
    },
    {
      "type": "text",
      "text": "• Các tùy chọn hình dạng cắt bế, vá cửa sổ và cán tùy chỉnh"
    },
    {
      "type": "text",
      "text": "Các tùy chọn hình dạng cắt bế, vá cửa sổ và cán tùy chỉnh"
    },
    {
      "type": "text",
      "text": "• 100% có thể tái chế, được chứng nhận FSC với mực sinh thái"
    },
    {
      "type": "text",
      "text": "100% có thể tái chế, bìa cứng được chứng nhận FSC với mực sinh thái"
    },
    {
      "type": "text",
      "text": "• Có sẵn lớp phủ có độ bóng, mờ hoặc mềm"
    },
    {
      "type": "text",
      "text": "Có sẵn lớp phủ có độ bóng, mờ hoặc mềm"
    },
    {
      "type": "text",
      "text": "• Thiết kế nhẹ nhưng cứng cáp, lý tưởng cho bán lẻ và thương mại điện tử"
    },
    {
      "type": "text",
      "text": "Thiết kế nhẹ nhưng cứng cáp, lý tưởng cho bán lẻ và thương mại điện tử"
    },
    {
      "type": "text",
      "text": "Giới thiệu về sản xuất của chúng tôi"
    },
    {
      "type": "text",
      "text": "XinYuan vận hành các nhà máy sản xuất thùng carton tích hợp đầy đủ được trang bị máy ép Heidelberg XL, chống màu CTP và dây chuyền gấp/dán tự động. In được chứng nhận G7 của chúng tôi đảm bảo màu sắc thương hiệu nhất quán, trong khi tiêu chuẩn sản xuất ISO 9001 đảm bảo độ chính xác ở mọi giai đoạn. Với sản lượng hàng tháng vượt quá 80 triệu thùng, chúng tôi cung cấp công suất có thể mở rộng và độ tin cậy chưa từng có cho các khách hàng toàn cầu đang tìm kiếm cả chất lượng và tính bền vững."
    },
    {
      "type": "heading",
      "level": 2,
      "text": "Tính bền vững và đổi mới"
    },
    {
      "type": "heading",
      "level": 2,
      "text": "Các ứng dụng"
    },
    {
      "type": "heading",
      "level": 2,
      "text": "Hỗ trợ sản xuất từ đầu đến cuối"
    },
    {
      "type": "text",
      "text": "XinYuan tập trung vào tìm nguồn cung ứng nguyên liệu có trách nhiệm và sản xuất ít chất thải. Chúng tôi in bằng mực làm từ đậu nành, thu hồi các mảnh giấy để tái chế và giảm thiểu chất thải lớp phủ."
    },
    {
      "type": "text",
      "text": "Đội ngũ R & D của chúng tôi liên tục phát triển các lớp phủ rào cản mới và thiết kế cấu trúc cân bằng giữa bảo vệ với hiệu suất sinh thái."
    },
    {
      "type": "text",
      "text": "Mỗi thùng carton được sản xuất đều phù hợp với các tiêu chuẩn tuân thủ toàn cầu như FSC®, GMI và ISO 9001 - củng cố cam kết của chúng tôi về sự xuất sắc trong bao bì bền vững."
    },
    {
      "type": "text",
      "text": "• Thực phẩm và đồ uống – thùng carton tráng cho hàng khô, ướp lạnh hoặc đông lạnh"
    },
    {
      "type": "text",
      "text": "Thực phẩm và đồ uống – thùng carton tráng cho hàng khô, ướp lạnh hoặc đông lạnh"
    },
    {
      "type": "text",
      "text": "• Beauty & Health – hộp gấp sang trọng với dập nổi hoặc dập giấy bạc"
    },
    {
      "type": "text",
      "text": "Beauty & Health – hộp gấp sang trọng với dập nổi hoặc dập giấy bạc"
    },
    {
      "type": "text",
      "text": "• Điện tử & FMCG – thùng carton chính xác đảm bảo an toàn vận chuyển"
    },
    {
      "type": "text",
      "text": "Điện tử & FMCG – thùng carton chính xác đảm bảo an toàn vận chuyển"
    },
    {
      "type": "text",
      "text": "• Thương mại điện tử – hộp phẳng, nhẹ được tối ưu hóa để đạt hiệu quả"
    },
    {
      "type": "text",
      "text": "Thương mại điện tử – hộp phẳng, nhẹ được tối ưu hóa để đạt hiệu quả"
    },
    {
      "type": "text",
      "text": "Từ thiết kế CAD và kiểm tra màu sắc đến lắp ráp cuối cùng, XinYuan cung cấp sản xuất thùng carton một cửa."
    },
    {
      "type": "text",
      "text": "Các kỹ sư đóng gói của chúng tôi hợp tác với khách hàng để tinh chỉnh hiệu suất, giảm chi phí và nâng cao nhận thức về thương hiệu. Chúng tôi cung cấp chất lượng nhất quán như nhau cho dù bạn đặt hàng 5.000 hay 5 triệu thùng — tất cả đều tuân theo các quy trình QC quốc tế nghiêm ngặt."
    },
    {
      "type": "heading",
      "level": 2,
      "text": "Thùng carton gấp cho mọi ngành công nghiệp"
    },
    {
      "type": "text",
      "text": "Các giải pháp thùng carton gấp của XinYuan tích hợp cấu trúc sáng tạo với độ chính xác trực quan. Chúng tôi thiết kế bao bì bảo vệ sản phẩm, hỗ trợ tự động hóa và truyền đạt nhận diện thương hiệu một cách hiệu quả. Cho dù bạn cần tay áo bán lẻ, hộp quà tặng hay thùng carton cấp thực phẩm, nhóm của chúng tôi đều cung cấp dịch vụ từ đầu đến cuối từ thiết kế đến giao hàng."
    },
    {
      "type": "text",
      "text": "Các ứng dụng:"
    },
    {
      "type": "image",
      "src": "/media/1.bip_.3002-copy.webp",
      "alt": "",
      "width": 720,
      "height": 480
    },
    {
      "type": "text",
      "text": "Tính bền vững và đổi mới"
    },
    {
      "type": "text",
      "text": "XinYuan tập trung vào tìm nguồn cung ứng nguyên liệu có trách nhiệm và sản xuất ít chất thải. Chúng tôi in bằng mực làm từ đậu nành, thu hồi các mảnh giấy để tái chế và giảm thiểu chất thải lớp phủ. Đội ngũ R & D của chúng tôi liên tục phát triển các lớp phủ rào cản mới và thiết kế cấu trúc cân bằng giữa bảo vệ với hiệu suất sinh thái. Mỗi thùng carton được sản xuất đều phù hợp với các tiêu chuẩn tuân thủ toàn cầu như FSC®, GMI và ISO 9001 - củng cố cam kết của chúng tôi về sự xuất sắc trong bao bì bền vững."
    },
    {
      "type": "text",
      "text": "Hỗ trợ sản xuất từ đầu đến cuốiTừ thiết kế CAD và kiểm tra màu sắc đến lắp ráp cuối cùng, XinYuan cung cấp sản xuất thùng carton một cửa. Các kỹ sư đóng gói của chúng tôi hợp tác với khách hàng để tinh chỉnh hiệu suất, giảm chi phí và nâng cao nhận thức về thương hiệu. Chúng tôi cung cấp chất lượng nhất quán như nhau cho dù bạn đặt hàng 5.000 hay 5 triệu thùng — tất cả đều tuân theo các quy trình QC quốc tế nghiêm ngặt."
    },
    {
      "type": "heading",
      "level": 2,
      "text": "Liên hệ với chúng tôi - Bao bì"
    },
    {
      "type": "image",
      "src": "https://jinhaoxy.com/wp-content/plugins/wpforms-lite/assets/images/submit-spin.svg",
      "alt": "Đang tải",
      "width": 26,
      "height": 26
    }
  ],
  "faqs": []
}