{
  "slug": "artificial-boxes",
  "title": "人工盒子",
  "parent": 0,
  "menu_order": 0,
  "blocks": [
    {
      "type": "heading",
      "level": 2,
      "text": "可靠的保护与易于搬运"
    },
    {
      "type": "text",
      "text": "越南和中国制造的重型塑料箱、带盖箱、隔板和收纳盒。专为仓库、零售和现场使用而建——可重复使用、易于清洁且具品牌竞争力。"
    },
    {
      "type": "heading",
      "level": 2,
      "text": "人工盒子——工业与物流用耐用塑料包装"
    },
    {
      "type": "text",
      "text": "我们越南的塑料包装制造商供应定制塑料箱、高密度聚乙烯箱和PP容器，注重耐用性、堆叠性和可见性。我们的产品设计用于工业、物流和零售应用，设计为长期使用和完全可回收。"
    },
    {
      "type": "text",
      "text": "新远制造人造塑料盒和托盘，设计注重强度、可重复使用和干净呈现。"
    },
    {
      "type": "text",
      "text": "我们在越南和中国的工厂生产聚丙烯（PP）和高密度聚乙烯（HDPE）箱，非常适合物流、零售和工业用途。它们完全可清洗、可堆叠且可回收，为现代供应链提供可持续的性能。"
    },
    {
      "type": "text",
      "text": "主要特色："
    },
    {
      "type": "text",
      "text": "• 注塑成型的PP/HDPE结构以增强耐用性"
    },
    {
      "type": "text",
      "text": "注塑成型的PP/HDPE结构以提升耐用性"
    },
    {
      "type": "text",
      "text": "• 可堆叠和可嵌套设计"
    },
    {
      "type": "text",
      "text": "可堆叠与嵌套设计"
    },
    {
      "type": "text",
      "text": "• 内壁光滑，便于清洁"
    },
    {
      "type": "text",
      "text": "内壁光滑，便于清洁"
    },
    {
      "type": "text",
      "text": "• 可选的盖子、隔板和排水孔"
    },
    {
      "type": "text",
      "text": "可选的盖子、隔板和排水孔"
    },
    {
      "type": "text",
      "text": "• 定制颜色和印刷品牌"
    },
    {
      "type": "text",
      "text": "定制色彩与印刷品牌"
    },
    {
      "type": "text",
      "text": "我们在越南和中国的工厂运营自动化成型和精密精加工线，每年生产超过100万个塑料箱和包装组件。每种设计都减轻重量，同时最大化强度——是一次性瓦楞纸包装的可持续替代方案。"
    },
    {
      "type": "text",
      "text": "应用："
    },
    {
      "type": "text",
      "text": "• 食品分销与冷链物流"
    },
    {
      "type": "text",
      "text": "食品分销与冷链物流"
    },
    {
      "type": "text",
      "text": "• 电子商务仓储"
    },
    {
      "type": "text",
      "text": "电子商务仓储"
    },
    {
      "type": "text",
      "text": "• 农业和工业储存"
    },
    {
      "type": "text",
      "text": "农业和工业储存"
    },
    {
      "type": "text",
      "text": "• 零售展示与运输解决方案"
    },
    {
      "type": "text",
      "text": "零售展示与运输解决方案"
    },
    {
      "type": "image",
      "src": "/media/factory-worker-sorting-plastic-caps-2025-03-18-14-56-46-utc.jpg",
      "alt": "工人正在将塑料盖分拣到大塑料箱中",
      "width": 720,
      "height": 480
    },
    {
      "type": "image",
      "src": "/media/dental-models-at-the-laboratory-2025-03-13-22-39-24-utc.jpg",
      "alt": "各种颜色的塑料篮子，里面装着小物品",
      "width": 719,
      "height": 480
    },
    {
      "type": "heading",
      "level": 2,
      "text": "满足各种需求的多功能解决方案"
    },
    {
      "type": "text",
      "text": "新远的人造塑料盒设计注重高效物流和跨行业的长期使用。它们设计得与现代仓库系统无缝集成——从输送带、货架到托盘存储。"
    },
    {
      "type": "text",
      "text": "• 分销与仓储——自动化线路可堆叠的托特和箱子"
    },
    {
      "type": "text",
      "text": "分销与仓储——自动化线路可堆叠的托特箱和箱子"
    },
    {
      "type": "text",
      "text": "• 零售与电子商务——用于订单履行的耐用箱"
    },
    {
      "type": "text",
      "text": "零售与电子商务——用于订单履行的耐用箱"
    },
    {
      "type": "text",
      "text": "• 食品行业——卫生、可清洗、食品级PP箱"
    },
    {
      "type": "text",
      "text": "食品行业——卫生、可清洗、食品级PP箱"
    },
    {
      "type": "text",
      "text": "• 电子与组装 — 静电安全导电盒"
    },
    {
      "type": "text",
      "text": "电子与组装 — ESD安全导电盒"
    },
    {
      "type": "text",
      "text": "我们还支持定制尺寸、品牌设计和颜色匹配，以符合您的公司身份。所有产品均符合ISO 9001质量控制标准，并可采用回收材料制造，以实现更环保的供应链。"
    },
    {
      "type": "heading",
      "level": 2,
      "text": "联系我们 - 包装"
    },
    {
      "type": "image",
      "src": "https://jinhaoxy.com/wp-content/plugins/wpforms-lite/assets/images/submit-spin.svg",
      "alt": "装载",
      "width": 26,
      "height": 26
    }
  ],
  "faqs": []
}